biolearn/__init__.py
biolearn/_version.py
biolearn/cache.py
biolearn/data_library.py
biolearn/defaults.py
biolearn/dunedin_pace.py
biolearn/hematology.py
biolearn/imputation.py
biolearn/load.py
biolearn/metadata.py
biolearn/model.py
biolearn/model_gallery.py
biolearn/mortality.py
biolearn/util.py
biolearn/visualize.py
biolearn/_utils/__init__.py
biolearn/_utils/docs.py
biolearn/data/450K_reinius_12_reference.csv
biolearn/data/AD_Bahado-Singh.csv
biolearn/data/Alcohol.csv
biolearn/data/AltumAge.csv
biolearn/data/AltumAge.pt
biolearn/data/BMI_McCartney.csv
biolearn/data/BMI_Reed.csv
biolearn/data/Bocklandt.csv
biolearn/data/BodyFatMcCartney.csv
biolearn/data/Bohlin.csv
biolearn/data/CVD_Westermann.csv
biolearn/data/DNAmClockCortical.csv
biolearn/data/DNAmTL.csv
biolearn/data/DepressionBarbu.csv
biolearn/data/DunedinPACE.csv
biolearn/data/DunedinPACE_Gold_Means.csv
biolearn/data/DunedinPoAm38.csv
biolearn/data/EPIC_salas_18_reference.csv
biolearn/data/EducationMcCartney.csv
biolearn/data/EpiTOC1.csv
biolearn/data/EpiTOC2.csv
biolearn/data/GrimAgeV1.csv
biolearn/data/GrimAgeV2.csv
biolearn/data/HDLCholesterolMcCartney.csv
biolearn/data/HRSInCHPhenoAge.csv
biolearn/data/Hannum.csv
biolearn/data/HepatoXu.csv
biolearn/data/Horvath1.csv
biolearn/data/Horvath2.csv
biolearn/data/Knight.csv
biolearn/data/LDLCholesterolMcCartney.csv
biolearn/data/LeeControl.csv
biolearn/data/LeeRefinedRobust.csv
biolearn/data/LeeRobust.csv
biolearn/data/Lin.csv
biolearn/data/Mayne.csv
biolearn/data/MiAge.csv
biolearn/data/Olink_uniprot_IDs.csv
biolearn/data/OrganAge1500Chronological.csv
biolearn/data/OrganAge1500Mortality.csv
biolearn/data/OrganAgeChronological.csv
biolearn/data/OrganAgeMortality.csv
biolearn/data/PEDBE.csv
biolearn/data/Pasta.csv
biolearn/data/PhenoAge.csv
biolearn/data/ProstateCancerKirby.csv
biolearn/data/REG.csv
biolearn/data/Smoking.csv
biolearn/data/StocH.csv
biolearn/data/StocP.csv
biolearn/data/StocZ.csv
biolearn/data/TotalCholesterolMcCartney.csv
biolearn-0.8.1.dist-info/METADATA
biolearn-0.8.1.dist-info/WHEEL
biolearn-0.8.1.dist-info/licenses/AUTHORS.rst
biolearn-0.8.1.dist-info/licenses/LICENSE
biolearn-0.8.1.dist-info/RECORD
