Metadata-Version: 2.3
Name: biolearn
Version: 0.8.1
Summary: Machine learning for biomarkers computing
Author: Biolearn developers
Maintainer-email: Martin Perez-Guevara <mperezguevara@gmail.com>
License: new BSD
Keywords: biomarker
Classifier: Intended Audience :: Developers
Classifier: Intended Audience :: Science/Research
Classifier: License :: OSI Approved
Classifier: Operating System :: OS Independent
Classifier: Programming Language :: C
Classifier: Programming Language :: Python
Classifier: Programming Language :: Python :: 3.10
Classifier: Programming Language :: Python :: 3.11
Classifier: Topic :: Scientific/Engineering
Classifier: Topic :: Software Development
Requires-Python: >=3.10
Requires-Dist: appdirs
Requires-Dist: cvxpy
Requires-Dist: ecos
Requires-Dist: matplotlib
Requires-Dist: numpy>=1.19.0
Requires-Dist: openpyxl
Requires-Dist: pandas>=2.1.0
Requires-Dist: pyyaml
Requires-Dist: requests
Requires-Dist: scikit-learn
Requires-Dist: scipy
Requires-Dist: xlrd
Provides-Extra: dev
Requires-Dist: black; extra == 'dev'
Requires-Dist: coverage; extra == 'dev'
Requires-Dist: flake8; extra == 'dev'
Requires-Dist: flake8-docstrings; extra == 'dev'
Requires-Dist: furo; extra == 'dev'
Requires-Dist: jupyterlab; extra == 'dev'
Requires-Dist: lifelines; extra == 'dev'
Requires-Dist: matplotlib>=3.3.0; extra == 'dev'
Requires-Dist: memory-profiler; extra == 'dev'
Requires-Dist: myst-parser; extra == 'dev'
Requires-Dist: numpydoc; extra == 'dev'
Requires-Dist: pytest-cov; extra == 'dev'
Requires-Dist: pytest>=6.0.0; extra == 'dev'
Requires-Dist: scikit-learn; extra == 'dev'
Requires-Dist: seaborn>=0.13.0; extra == 'dev'
Requires-Dist: sphinx; extra == 'dev'
Requires-Dist: sphinx-copybutton; extra == 'dev'
Requires-Dist: sphinx-design; extra == 'dev'
Requires-Dist: sphinx-gallery; extra == 'dev'
Requires-Dist: sphinxcontrib-bibtex; extra == 'dev'
Requires-Dist: sphinxext-opengraph; extra == 'dev'
Requires-Dist: torch; extra == 'dev'
Requires-Dist: torchvision; extra == 'dev'
Provides-Extra: doc
Requires-Dist: black; extra == 'doc'
Requires-Dist: coverage; extra == 'doc'
Requires-Dist: flake8; extra == 'doc'
Requires-Dist: flake8-docstrings; extra == 'doc'
Requires-Dist: furo; extra == 'doc'
Requires-Dist: lifelines; extra == 'doc'
Requires-Dist: matplotlib>=3.3.0; extra == 'doc'
Requires-Dist: memory-profiler; extra == 'doc'
Requires-Dist: myst-parser; extra == 'doc'
Requires-Dist: numpydoc; extra == 'doc'
Requires-Dist: seaborn>=0.13.0; extra == 'doc'
Requires-Dist: sphinx; extra == 'doc'
Requires-Dist: sphinx-copybutton; extra == 'doc'
Requires-Dist: sphinx-design; extra == 'doc'
Requires-Dist: sphinx-gallery; extra == 'doc'
Requires-Dist: sphinxcontrib-bibtex; extra == 'doc'
Requires-Dist: sphinxext-opengraph; extra == 'doc'
Provides-Extra: examples
Requires-Dist: lifelines; extra == 'examples'
Provides-Extra: plotting
Requires-Dist: matplotlib>=3.3.0; extra == 'plotting'
Requires-Dist: seaborn>=0.13.0; extra == 'plotting'
Provides-Extra: test
Requires-Dist: coverage; extra == 'test'
Requires-Dist: pytest-cov; extra == 'test'
Requires-Dist: pytest>=6.0.0; extra == 'test'
